{
  "version": "0.1.0",
  "highlights": [
    {
      "type": "new",
      "title": "本地优先的 AI 伴读",
      "description": "Yomitomo 首个版本：导入文章、阅读视图、目录与字号，数据保存在本机。",
      "audience": "all"
    },
    {
      "type": "new",
      "title": "高亮、批注与讨论",
      "description": "选中文本创建高亮、添加批注类型、继续评论并维护讨论线程。",
      "audience": "reader"
    },
    {
      "type": "new",
      "title": "AI 伴读助手与主动精读",
      "description": "配置阅读助手围绕原文与选区生成批注，或编排多助手对章节精读。",
      "audience": "ai"
    },
    {
      "type": "new",
      "title": "阅读库与统计",
      "description": "保存文章、批注、评论和阅读状态，沉淀本地阅读趋势。",
      "audience": "all"
    }
  ]
}
